test_cm_py_module/__init__.py
test_cm_py_module/calculator.py
test_cm_py_module-0.1.0.dist-info/licenses/LICENSE
test_cm_py_module-0.1.0.dist-info/METADATA
test_cm_py_module-0.1.0.dist-info/WHEEL
test_cm_py_module-0.1.0.dist-info/top_level.txt
test_cm_py_module-0.1.0.dist-info/RECORD
